[{"title":"Alemannenstraße","lat":"52.633532","lng":"13.280754","date":"vor 1922","link":"Alemannen","wikidata":"Q132990","gender":""},{"title":"Am Ausblick","lat":"52.632047","lng":"13.272858","date":"1930-08-04","link":"","wikidata":null,"gender":""},{"title":"Am Biberbau","lat":"52.628505","lng":"13.297362","date":"1930-08-04","link":"","wikidata":null,"gender":""},{"title":"Am Eichenhain","lat":"52.632646","lng":"13.266077","date":"1910-00-00","link":"","wikidata":null,"gender":""},{"title":"Am Grünen Hof","lat":"52.632282","lng":"13.277450","date":"1910-00-00","link":"","wikidata":null,"gender":""},{"title":"Am Grünen Zipfel","lat":"52.629859","lng":"13.283544","date":"1910-00-00","link":"","wikidata":null,"gender":""},{"title":"Am Kahlschlag","lat":"52.629260","lng":"13.274016","date":"1930-08-04","link":"","wikidata":null,"gender":""},{"title":"Am Kringel","lat":"52.632073","lng":"13.274274","date":"1930-08-04","link":"Kringel","wikidata":"Q6437064","gender":""},{"title":"Am Pfingstberg","lat":"52.625353","lng":"13.302813","date":"1930-08-04","link":"","wikidata":null,"gender":""},{"title":"Am Pilz","lat":"52.644105","lng":"13.303628","date":"1930-08-04","link":"","wikidata":null,"gender":""},{"title":"Am Poloplatz","lat":"52.644912","lng":"13.287234","date":"1967-04-01","link":"Polo (Sport)","wikidata":"","gender":""},{"title":"Am Priesterberg","lat":"52.634990","lng":"13.268909","date":"1910-00-00","link":"","wikidata":null,"gender":""},{"title":"Am Querschlag","lat":"52.632203","lng":"13.279209","date":"1930-08-04","link":"Schlag (Forstwirtschaft)","wikidata":"Q496707","gender":""},{"title":"Am Rosenanger","lat":"52.628270","lng":"13.302898","date":"1910-00-00","link":"","wikidata":null,"gender":""},{"title":"An der Buche","lat":"52.630015","lng":"13.286204","date":"1910-00-00","link":"Buchen","wikidata":"Q25403","gender":""},{"title":"Ansgarstraße","lat":"52.638584","lng":"13.268437","date":"1930-08-04","link":"Ansgar","wikidata":"Q110299","gender":"male"},{"title":"Ariadnestraße","lat":"52.63666","lng":"13.29221","date":"1930-08-04","link":"Ariadne","wikidata":"Q184874","gender":"female"},{"title":"Artuswall","lat":"52.62947","lng":"13.27033","date":"1930-08-04","link":"Artus","wikidata":"Q45792","gender":"male"},{"title":"Askaloner Weg","lat":"52.62811","lng":"13.28972","date":"1931-01-23","link":"Aschkelon","wikidata":"Q60956","gender":""},{"title":"Auber Steig","lat":"52.62999","lng":"13.29882","date":"1930-08-04","link":"Aub","wikidata":"Q376558","gender":""},{"title":"Barthstraße","lat":"52.64371","lng":"13.28723","date":"1961-04-10","link":"Theodor Barth","wikidata":"Q15148978","gender":"male"},{"title":"Benediktinerstraße","lat":"52.63153","lng":"13.27685","date":"1910-00-00","link":"Benediktiner","wikidata":"Q131132","gender":""},{"title":"Bergfelder Stadtweg (Waldweg)","lat":"52.65759","lng":"13.30474","date":"1910-00-00","link":"Bergfelde","wikidata":"Q16054629","gender":""},{"title":"Bergfelder Weg","lat":"52.64317","lng":"13.29466","date":"1976-07-01","link":"Bergfelde","wikidata":"Q16054629","gender":""},{"title":"Bieselheider Weg","lat":"52.64228","lng":"13.30434","date":"1930-08-04","link":"Bieselheide","wikidata":"Q858101","gender":""},{"title":"Bifröstweg","lat":"52.62931","lng":"13.26548","date":"1931-01-23","link":"Bifröst (Mythologie)","wikidata":"Q208525","gender":""},{"title":"Bulgenbachweg","lat":"52.64147","lng":"13.30672","date":"1931-04-01","link":"Hans Müller (Bauernkrieg)","wikidata":"Q76365","gender":"male"},{"title":"Bundschuhweg","lat":"52.63976","lng":"13.30483","date":"1930-08-04","link":"Bundschuh","wikidata":"Q694142","gender":""},{"title":"Burgfrauenstraße","lat":"52.62944","lng":"13.29449","date":"1910-00-00","link":"","wikidata":null,"gender":""},{"title":"Criolloweg","lat":"52.64444","lng":"13.28500","date":"2001-02-02","link":"Criollo (Pferd)","wikidata":"Q1140113","gender":""},{"title":"Der Zwinger","lat":"52.63166","lng":"13.29329","date":"1910-00-00","link":"Zwinger (Architektur)","wikidata":"Q244824","gender":""},{"title":"Dinkelsbühler Steig","lat":"52.63291","lng":"13.29487","date":"1937-03-11","link":"Dinkelsbühl","wikidata":"Q491743","gender":""},{"title":"Donnersmarckallee","lat":"52.62801","lng":"13.27633","date":"1930-08-04","link":"Guido Henckel von Donnersmarck","wikidata":"Q68362","gender":"male"},{"title":"Donnersmarckplatz","lat":"52.62986","lng":"13.27960","date":"1926-11-09","link":"Guido Henckel von Donnersmarck","wikidata":"Q68362","gender":"male"},{"title":"Edelhofdamm","lat":"52.63535","lng":"13.29925","date":"1937-08-31","link":"Heinrich I. (Ostfrankenreich)","wikidata":"","gender":""},{"title":"Elfriedestraße (Waldweg)","lat":"52.65665","lng":"13.29758","date":"1910-00-00","link":"Elfriede","wikidata":"Q18327552","gender":""},{"title":"Eltviller Straße","lat":"52.63218","lng":"13.30191","date":"1910-00-00","link":"Eltville am Rhein","wikidata":"Q275193","gender":""},{"title":"Enkircher Straße","lat":"52.63317","lng":"13.30517","date":"1930-08-04","link":"Enkirch","wikidata":"Q553838","gender":""},{"title":"Eßlinger Steig","lat":"52.63356","lng":"13.30736","date":"1930-08-04","link":"Esslingen am Neckar","wikidata":"Q3786","gender":""},{"title":"Forstweg","lat":"52.62533","lng":"13.27749","date":"vor 1910","link":"","wikidata":null,"gender":""},{"title":"Franziskastraße (Waldweg)","lat":"52.65771","lng":"13.29897","date":"1910-00-00","link":"Franziska","wikidata":"Q877792","gender":""},{"title":"Frohnauer Straße","lat":"52.62772","lng":"13.28616","date":"1937-08-06","link":"Berlin-Frohnau","wikidata":"Q15639136","gender":""},{"title":"Fuchsring","lat":"52.64262","lng":"13.28526","date":"2002-02-22","link":"Fuchs (Pferd)","wikidata":"Q8331","gender":""},{"title":"Fuchssteinerweg","lat":"52.63598","lng":"13.29590","date":"1931-01-31","link":"Deutscher Bauernkrieg","wikidata":"Q154031","gender":""},{"title":"Fürstendamm","lat":"52.63142","lng":"13.30007","date":"1910-00-00","link":"Fürst","wikidata":"Q18244","gender":""},{"title":"Gawanstraße","lat":"52.62923","lng":"13.27556","date":"1930-08-04","link":"Gawain","wikidata":"Q831685","gender":"male"},{"title":"Geierpfad","lat":"52.64634","lng":"13.30522","date":"1930-08-04","link":"Geier (Vogel)","wikidata":"Q123120","gender":""},{"title":"Glambecker Weg","lat":"52.62444","lng":"13.29032","date":"1936-06-13","link":"Friedrichswalde","wikidata":"Q241395","gender":""},{"title":"Gollanczstraße","lat":"52.64213","lng":"13.28642","date":"1955-07-26","link":"Victor Gollancz","wikidata":"Q574400","gender":"male"},{"title":"Gralsburgsteig","lat":"52.637412","lng":"13.284531","date":"1930-08-04","link":"Gralsburg","wikidata":null,"gender":""},{"title":"Gralsritterweg","lat":"52.636683","lng":"13.275518","date":"1930-08-04","link":"Heiliger Gral","wikidata":"Q162808","gender":""},{"title":"Graneweg","lat":"52.627046","lng":"13.265578","date":"1931-04-10","link":"Siegfried der Drachentöter","wikidata":"Q537554","gender":"male"},{"title":"Gurnemanzpfad","lat":"52.639313","lng":"13.269897","date":"1967-04-01","link":"Gurnemanz","wikidata":"Q1247232","gender":""},{"title":"Gutshofstraße","lat":"52.638063","lng":"13.300323","date":"1926-11-09","link":"","wikidata":null,"gender":""},{"title":"Haflingerpfad","lat":"52.646006","lng":"13.285925","date":"2002-02-22","link":"Haflinger","wikidata":"Q609630","gender":""},{"title":"Hainbuchenstraße","lat":"52.636423","lng":"13.269124","date":"1910-00-00","link":"Hainbuche","wikidata":"Q158776","gender":""},{"title":"Hambacher Weg","lat":"52.630797","lng":"13.302684","date":"1930-08-04","link":"Hambach an der Weinstraße","wikidata":"Q393532","gender":""},{"title":"Hangweg","lat":"52.630458","lng":"13.265691","date":"1936-09-24","link":"","wikidata":null,"gender":""},{"title":"Hattenheimer Straße","lat":"52.630758","lng":"13.295764","date":"1930-08-04","link":"Hattenheim","wikidata":"Q1589004","gender":""},{"title":"Heerruferweg","lat":"52.635921","lng":"13.267933","date":"1936-09-24","link":"Werber (Beruf)","wikidata":"","gender":""},{"title":"Helweg","lat":"52.628218","lng":"13.265390","date":"1930-08-04","link":"Hel (Mythologie)","wikidata":"Q191589","gender":"female"},{"title":"Hofjägerallee","lat":"52.636891","lng":"13.298349","date":"1910-00-00","link":"Hofstaat","wikidata":"Q1134237","gender":""},{"title":"Hohenheimer Straße","lat":"52.634053","lng":"13.299465","date":"1910-00-00","link":"Hohenheim (Stuttgart)","wikidata":"Q521992","gender":""},{"title":"Horandweg","lat":"52.637803","lng":"13.273845","date":"1930-08-04","link":"Gudrunlied","wikidata":"Q491164","gender":""},{"title":"Hubertusweg","lat":"52.656029","lng":"13.300366","date":"1910-00-00","link":"Hubertus von Lüttich","wikidata":"Q159834","gender":"male"},{"title":"Huttenstraße","lat":"52.641058","lng":"13.294787","date":"1910-00-00","link":"Ulrich von Hutten","wikidata":"Q77107","gender":"male"},{"title":"Idastraße (Waldweg)","lat":"52.656648","lng":"13.294809","date":"1910-00-00","link":"Ida (Vorname)","wikidata":"Q1509923","gender":""},{"title":"Im Amseltal","lat":"52.636475","lng":"13.281827","date":"1910-00-00","link":"Tal","wikidata":"Q39816","gender":""},{"title":"Im Fischgrund","lat":"52.629429","lng":"13.300452","date":"1930-08-04","link":"","wikidata":null,"gender":""},{"title":"Invalidensiedlung","lat":"52.657722","lng":"13.284187","date":"1938","link":"Invalidensiedlung","wikidata":"Q1671654","gender":""},{"title":"Jägerstieg (Waldweg)","lat":"52.653491","lng":"13.299433","date":"1910-00-00","link":"Jäger","wikidata":"Q315316","gender":""},{"title":"Jostweg","lat":"52.638272","lng":"13.303885","date":"1931-01-31","link":"Joß Fritz","wikidata":"Q95253","gender":"male"},{"title":"Kammgasse","lat":"52.626264","lng":"13.286462","date":"1930-08-04","link":"Gebirgskamm","wikidata":"Q740445","gender":""},{"title":"Karmeliterweg","lat":"52.627645","lng":"13.279810","date":"1930-08-04","link":"Karmeliten","wikidata":"Q186277","gender":""},{"title":"Kasinoweg","lat":"52.630588","lng":"13.291869","date":"1910","link":"","wikidata":null,"gender":""},{"title":"Katzensteg","lat":"52.634756","lng":"13.295431","date":"1930-08-04","link":"Hermann Sudermann","wikidata":"Q65448","gender":"male"},{"title":"Klarastraße","lat":"52.657435","lng":"13.292245","date":"1910-00-00","link":"Klara","wikidata":"Q6490829","gender":"female"},{"title":"Knappenpfad","lat":"52.630198","lng":"13.290496","date":"1930-08-04","link":"Schildknappe","wikidata":"Q579516","gender":""},{"title":"Kniggeweg","lat":"52.639626","lng":"13.284702","date":"1930-08-04","link":"Adolph Knigge","wikidata":"Q213681","gender":"male"},{"title":"Königsbacher Zeile","lat":"52.640225","lng":"13.295517","date":"1930-08-04","link":"Königsbach an der Weinstraße","wikidata":"Q282991","gender":""},{"title":"Konzer Platz","lat":"52.638741","lng":"13.298607","date":"1936-09-24","link":"Konz","wikidata":"Q503185","gender":""},{"title":"Koppelweg","lat":"52.636761","lng":"13.299079","date":"1936-09-24","link":"Weideland","wikidata":null,"gender":""},{"title":"Kreuzritterstraße","lat":"52.629130","lng":"13.291612","date":"1927-02-18","link":"Kreuzzug","wikidata":"Q12546","gender":""},{"title":"Langohrzeile","lat":"52.629937","lng":"13.306332","date":"1961-01-09","link":"Feldhase","wikidata":"Q26838","gender":""},{"title":"Laurinsteig","lat":"52.636397","lng":"13.272536","date":"1930-08-04","link":"König Laurins Rosengarten","wikidata":"Q1712676","gender":""},{"title":"Lichtungsweg","lat":"52.632750","lng":"13.266892","date":"1930-08-04","link":"","wikidata":null,"gender":""},{"title":"Lipizzanerweg","lat":"52.645811","lng":"13.285046","date":"2001-02-02","link":"Lipizzaner","wikidata":"Q217671","gender":""},{"title":"Ludolfingerplatz","lat":"52.632464","lng":"13.287964","date":"1937-05-20","link":"Liudolfinger","wikidata":"Q157106","gender":""},{"title":"Ludolfingerweg","lat":"52.632828","lng":"13.279467","date":"1937-05-20","link":"Liudolfinger","wikidata":"Q157106","gender":""},{"title":"Malwinestraße","lat":"52.657598","lng":"13.290491","date":"nach 1990","link":"Malvina","wikidata":"Q14539509","gender":""},{"title":"Markgrafenstraße","lat":"52.635667","lng":"13.297062","date":"1910-00-00","link":"Markgraf","wikidata":"Q157802","gender":""},{"title":"Mattersburger Weg","lat":"52.626629","lng":"13.283501","date":"1930-8-04","link":"Mattersburg","wikidata":"Q250832","gender":""},{"title":"Maximiliankorso","lat":"52.634261","lng":"13.277063","date":"1910-00-00","link":"Maximilian I. (HRR)","wikidata":"","gender":""},{"title":"Mehringer Straße","lat":"52.640043","lng":"13.297405","date":"1933-07-10","link":"Mehring (Mosel)","wikidata":"Q1917569","gender":""},{"title":"Merlinweg","lat":"52.633896","lng":"13.266678","date":"1961-04-04","link":"Merlin","wikidata":"Q131918","gender":""},{"title":"Minheimer Straße","lat":"52.636891","lng":"13.286633","date":"1938-09-23","link":"Minheim","wikidata":"Q524796","gender":""},{"title":"Münchener Straße","lat":"52.635635","lng":"13.274091","date":"1910-00-00","link":"München","wikidata":"Q1726","gender":""},{"title":"Mustangweg","lat":"52.646304","lng":"13.285845","date":"2002-02-22","link":"Mustang (Pferd)","wikidata":"Q211848","gender":""},{"title":"Neubrücker Straße","lat":"52.639463","lng":"13.273534","date":"1961-01-09","link":"Hennigsdorf","wikidata":"Q583462","gender":""},{"title":"Nibelungenstraße","lat":"52.636970","lng":"13.279681","date":"1910-00-00","link":"Nibelungen (Volk)","wikidata":"Q411976","gender":""},{"title":"Olwenstraße","lat":"52.627332","lng":"13.272772","date":"1930-08-04","link":"Olwen","wikidata":"Q2021381","gender":""},{"title":"Oppenheimer Weg","lat":"52.634339","lng":"13.305538","date":"1930-08-04","link":"Oppenheim","wikidata":"Q518690","gender":""},{"title":"Oranienburger Chaussee","lat":"52.645472","lng":"13.299127","date":"nach 1933","link":"Oranienburg","wikidata":"Q14808","gender":""},{"title":"Ortwinstraße","lat":"52.636162","lng":"13.281870","date":"1935-02-12","link":"Ortwin","wikidata":"Q1676861","gender":""},{"title":"Otternweg","lat":"52.627541","lng":"13.298950","date":"1935-02-12","link":"Otter","wikidata":"Q200184","gender":""},{"title":"Pfadfinderweg","lat":"52.628570","lng":"13.270004","date":"1935-02-12","link":"Pfadfinder","wikidata":"Q872181","gender":""},{"title":"Pilgersdorfer Weg","lat":"52.628804","lng":"13.267525","date":"1930-08-04","link":"Pilgersdorf","wikidata":"Q663460","gender":""},{"title":"Pirschweg","lat":"52.626375","lng":"13.270347","date":"1936-09-24","link":"Jagd#Einzeljagd","wikidata":"Q2096867","gender":""},{"title":"Ponyweg","lat":"52.647269","lng":"13.285561","date":"2002-02-22","link":"Pony (Pferd)","wikidata":"Q188828","gender":""},{"title":"Rappenweg","lat":"52.643643","lng":"13.285756","date":"2002-02-22","link":"Rappe","wikidata":"Q10649760","gender":""},{"title":"Rauentaler Straße","lat":"52.645772","lng":"13.301976","date":"1910-00-00","link":"Rauenthal (Rheingau)","wikidata":"Q2133129","gender":""},{"title":"Remstaler Straße","lat":"52.638298","lng":"13.302298","date":"1931-01-23","link":"Remstal","wikidata":"Q2143171","gender":""},{"title":"Rodelbahnpfad","lat":"52.632386","lng":"13.305291","date":"1936-09-24","link":"Rodeln","wikidata":"Q3266340","gender":""},{"title":"Rosamundeweg","lat":"52.655626","lng":"13.299133","date":"1910-00-00","link":"Rosamund","wikidata":"Q2166577","gender":""},{"title":"Rosenplüterweg","lat":"52.642464","lng":"13.307056","date":"1930-08-04","link":"Hans Rosenplüt","wikidata":"Q105816","gender":"male"},{"title":"Rüdesheimer Straße","lat":"52.632954","lng":"13.300204","date":"1910-00-00","link":"Rüdesheim am Rhein","wikidata":"Q628118","gender":""},{"title":"Schönfließer Straße","lat":"52.642647","lng":"13.296161","date":"vor 1912","link":"Schönfließ (Oberhavel)","wikidata":"Q1507415","gender":""},{"title":"Schwarzkittelweg","lat":"52.645277","lng":"13.303370","date":"1930-08-04","link":"Wildschwein","wikidata":"Q58697","gender":""},{"title":"Senheimer Straße","lat":"52.639548","lng":"13.292127","date":"1930-08-04","link":"Senheim","wikidata":"Q653097","gender":""},{"title":"Sigismundkorso","lat":"52.630188","lng":"13.277573","date":"1910-00-00","link":"Sigismund (HRR)","wikidata":"Q57124","gender":"male"},{"title":"Söllerpfad","lat":"52.638695","lng":"13.283157","date":"1936-09-24","link":"Söller","wikidata":"Q5565749","gender":""},{"title":"Speerweg","lat":"52.634684","lng":"13.267263","date":"1930-08-04","link":"Speer","wikidata":"Q44475","gender":""},{"title":"Staehleweg","lat":"52.655390","lng":"13.286391","date":"1971-04-23","link":"Wilhelm Staehle","wikidata":"Q98263","gender":"male"},{"title":"Stolzingstraße","lat":"52.637591","lng":"13.279516","date":"1961-01-09","link":"Die Meistersinger von Nürnberg","wikidata":"Q465540","gender":""},{"title":"Straße 52 (Waldweg)","lat":"52.650514","lng":"13.301809","date":"vor 1930","link":"","wikidata":null,"gender":""},{"title":"Straße 114a (Hasensprung)","lat":"52.628866","lng":"13.306195","date":"1961-01-09","link":"","wikidata":null,"gender":""},{"title":"Tannenstraße","lat":"52.631533","lng":"13.285797","date":"1926-11-09","link":"Tannen","wikidata":"Q25350","gender":""},{"title":"Unkeler Pfad","lat":"52.631583","lng":"13.306171","date":"1938-02-19","link":"Unkel","wikidata":"Q498589","gender":""},{"title":"Utestraße","lat":"52.658854","lng":"13.296665","date":"1961-01-09","link":"Ute (Vorname)","wikidata":"Q1253290","gender":""},{"title":"Wahnfriedstraße","lat":"52.636631","lng":"13.283452","date":"1925-03-23","link":"Haus Wahnfried","wikidata":"Q2540417","gender":""},{"title":"Walporzheimer Straße","lat":"52.630432","lng":"13.299857","date":"1910","link":"Walporzheim","wikidata":"Q2543201","gender":""},{"title":"Weislingenstraße","lat":"52.641232","lng":"13.301195","date":"1930-08-04","link":"","wikidata":null,"gender":""},{"title":"Welfenallee","lat":"52.628671","lng":"13.286998","date":"1938-05-11","link":"Welfen","wikidata":"Q156433","gender":""},{"title":"Wildkanzelweg","lat":"52.645537","lng":"13.303757","date":"1930-08-04","link":"Hochsitz","wikidata":"Q1279822","gender":""},{"title":"Wilsbergzeile","lat":"52.631456","lng":"13.265758","date":"1936-09-24","link":"","wikidata":null,"gender":""},{"title":"Wiltinger Straße","lat":"52.636078","lng":"13.290174","date":"1937-04-20","link":"Wiltingen","wikidata":"Q161930","gender":""},{"title":"Zeltinger Platz","lat":"52.633714","lng":"13.290914","date":"1937-06-08","link":"Zeltingen-Rachtig","wikidata":"Q189241","gender":""},{"title":"Zeltinger Straße","lat":"52.638185","lng":"13.296665","date":"1937-08-06","link":"Zeltingen-Rachtig","wikidata":"Q189241","gender":""},{"title":"Zerndorfer Weg","lat":"52.638610","lng":"13.299669","date":"1930-08-04","link":"Vorwerk (Gutshof)","wikidata":"Q503271","gender":""},{"title":"Zwergenweg","lat":"52.626095","lng":"13.276768","date":"1930-08-04","link":"","wikidata":null,"gender":""}]